einexpr/__init__.py
einexpr/array_api/__init__.py
einexpr/array_api/_types.py
einexpr/array_api/constants.py
einexpr/array_api/creation_functions.py
einexpr/array_api/data_type_functions.py
einexpr/array_api/data_types.py
einexpr/array_api/dimension.py
einexpr/array_api/einarray_object.py
einexpr/array_api/elementwise_functions.py
einexpr/array_api/linalg.py
einexpr/array_api/linear_algebra_functions.py
einexpr/array_api/manipulation_functions.py
einexpr/array_api/searching_functions.py
einexpr/array_api/set_functions.py
einexpr/array_api/sorting_functions.py
einexpr/array_api/statistical_functions.py
einexpr/array_api/utility_functions.py
einexpr/backends/__init__.py
einexpr/backends/backends.py
einexpr/backends/raw_ops.py
einexpr/backends/tracer.py
einexpr/dimension_utils/__init__.py
einexpr/dimension_utils/dim_calcs.py
einexpr/dimension_utils/exceptions.py
einexpr/dimension_utils/out_dims_calculator.py
einexpr/types/__init__.py
einexpr/types/types.py
einexpr/utils/__init__.py
einexpr/utils/exceptions.py
einexpr/utils/utils.py
einexpr-0.3.2.dist-info/LICENSE
einexpr-0.3.2.dist-info/WHEEL
einexpr-0.3.2.dist-info/METADATA
einexpr-0.3.2.dist-info/RECORD
