Metadata-Version: 2.1
Name: einexpr
Version: 0.3.2
Summary: 
Author: IsaacBreen
Author-email: 57783927+IsaacBreen@users.noreply.github.com
Requires-Python: >=3.9,<4.0
Classifier: Programming Language :: Python :: 3
Classifier: Programming Language :: Python :: 3.10
Classifier: Programming Language :: Python :: 3.9
Requires-Dist: colorama (>=0.4.3,<0.5.0)
Requires-Dist: lark (>=1.1.2,<2.0.0)
Requires-Dist: numpy (>=1.22.4,<2.0.0)
